{
    "TOPIC_NODE_ID_dimmer":[
        {
            "All":65535
        },
        {
            "Channel":0,
            "Value":65535
        },
        {
            "Array":[65535,0,0,65535]
        },
        {
            "List":[
                {"1":65535},
                {"2":0},
                {"4":1200}
            ]
        }
    ],
    "TOPIC_MeshRF":[
        {
            "control":{
                "msg_type":"p2p",
                "resp_type":"msg_ack",
                "direction":"message",
                "qos":"ACK",
                "timetolive":2
            },
            "pid":"dimmer",
            "dest":25,
            "payload":["0x08","0xF0"]
        },
        {
            "control":{
                "direction":"message"
            },
            "pid":"dimmer",
            "dest":25,
            "payload":["0x08","0xF0"]
        },
        {
            "control_options":{
                "msg_type":[
                    "broadcast",
                    {"p2p":{
                        "resp_type":[
                            {"msg_ack":{
                                "direction":
                                [
                                    {"message":{"qos":["SendACK","DoNotSendACK"]}},
                                    "acknowledge"
                                ]
                                }},
                                {"req_resp":{"direction":["request","response"]
                                    }
                                }
                        ]
                        }
                    }
                ],
                "timetolive":[0,15]
            },
            "pid_options":["dimmer"]
        }
    ],
    "TOPIC_RawRF":[
        "0x06 0x7B 0x17 0x19 0x00 0x00",
        "0x06 0x7B 0x17 0x19 0x08 0xF0"
    ]
}
